{"version": "1", "message": "ERROR: Hidden Testcases server unreachable.", "problem_id": "ads2_m7_a1_1", "user_id": "prathyushab14", "score": {"sample": {"0": {"execution_time": 0.5399541854858398, "passed": true}, "1": {"execution_time": 0.16112780570983887, "passed": true}, "2": {"execution_time": 0.2010354995727539, "passed": true}, "3": {"execution_time": 0.16150259971618652, "passed": true}, "4": {"execution_time": 0.17145633697509766, "passed": true}, "5": {"execution_time": 0.15541410446166992, "passed": true}}}, "check_style_score": "0/1"}